{
  "_versions": {
    "salvar-projeto": 64,
    "update-project": 55,
    "chat-consulta": 52,
    "chat-agent": 49,
    "welcome-email": 50,
    "generate-report": 71,
    "sync-sharepoint": 48,
    "sync-teams": 48,
    "enviar-confirmacao-email": 48,
    "parse-budget-pdf": 49,
    "process-budget-pdf": 47,
    "process-remittance": 42,
    "process-billing-automation": 19,
    "generate-cross-system-code": 16,
    "exchange-cross-system-code": 16,
    "sync-fechamentos-automatica": 13
  }
}